{
  "dados": [
    {
      "ano": 2026,
      "mes": 5,
      "tipoDespesa": "COMBUSTÍVEIS E LUBRIFICANTES.",
      "codDocumento": "8098973",
      "tipoDocumento": "Nota Fiscal Eletrônica",
      "codTipoDocumento": 4,
      "dataDocumento": "2026-05-06T21:02:02",
      "numDocumento": "705510",
      "valorDocumento": 300.11,
      "urlDocumento": "http://www.camara.leg.br/cota-parlamentar/nota-fiscal-eletronica?ideDocumentoFiscal=8098973",
      "nomeFornecedor": "072 - 403 SUL - CASCOL COMBUSTIVEIS PARA VEICULOS LTDA",
      "cnpjCpfFornecedor": "00306597007290",
      "valorLiquido": 300.11,
      "valorGlosa": 0.0,
      "numRessarcimento": "",
      "codLote": 2235630,
      "parcela": 0
    },
    {
      "ano": 2026,
      "mes": 5,
      "tipoDespesa": "COMBUSTÍVEIS E LUBRIFICANTES.",
      "codDocumento": "8098963",
      "tipoDocumento": "Nota Fiscal Eletrônica",
      "codTipoDocumento": 4,
      "dataDocumento": "2026-05-13T20:53:12",
      "numDocumento": "1399659",
      "valorDocumento": 307.43,
      "urlDocumento": "http://www.camara.leg.br/cota-parlamentar/nota-fiscal-eletronica?ideDocumentoFiscal=8098963",
      "nomeFornecedor": "076 - MELHOR 10 - CASCOL COMBUSTIVEIS PARA VEICULOS LTDA",
      "cnpjCpfFornecedor": "00306597007614",
      "valorLiquido": 307.43,
      "valorGlosa": 0.0,
      "numRessarcimento": "",
      "codLote": 2235630,
      "parcela": 0
    },
    {
      "ano": 2026,
      "mes": 5,
      "tipoDespesa": "COMBUSTÍVEIS E LUBRIFICANTES.",
      "codDocumento": "8124191",
      "tipoDocumento": "Nota Fiscal Eletrônica",
      "codTipoDocumento": 4,
      "dataDocumento": "2026-05-20T15:17:50",
      "numDocumento": "595068",
      "valorDocumento": 278.77,
      "urlDocumento": "http://www.camara.leg.br/cota-parlamentar/nota-fiscal-eletronica?ideDocumentoFiscal=8124191",
      "nomeFornecedor": "19 - 303 SUL - CASCOL COMBUSTIVEIS PARA VEICULOS LTDA",
      "cnpjCpfFornecedor": "00306597001926",
      "valorLiquido": 278.77,
      "valorGlosa": 0.0,
      "numRessarcimento": "",
      "codLote": 2248634,
      "parcela": 0
    },
    {
      "ano": 2026,
      "mes": 5,
      "tipoDespesa": "COMBUSTÍVEIS E LUBRIFICANTES.",
      "codDocumento": "8124195",
      "tipoDocumento": "Nota Fiscal Eletrônica",
      "codTipoDocumento": 4,
      "dataDocumento": "2026-05-27T16:42:18",
      "numDocumento": "73216",
      "valorDocumento": 299.71,
      "urlDocumento": "http://www.camara.leg.br/cota-parlamentar/nota-fiscal-eletronica?ideDocumentoFiscal=8124195",
      "nomeFornecedor": "AUTO POSTO 303 NORTE LTDA",
      "cnpjCpfFornecedor": "38194212000120",
      "valorLiquido": 299.71,
      "valorGlosa": 0.0,
      "numRessarcimento": "",
      "codLote": 2248634,
      "parcela": 0
    },
    {
      "ano": 2026,
      "mes": 5,
      "tipoDespesa": "DIVULGAÇÃO DA ATIVIDADE PARLAMENTAR.",
      "codDocumento": "8109310",
      "tipoDocumento": "Nota Fiscal",
      "codTipoDocumento": 0,
      "dataDocumento": "2026-06-01T00:00:00",
      "numDocumento": "102",
      "valorDocumento": 6000.0,
      "urlDocumento": "https://www.camara.leg.br/cota-parlamentar/documentos/publ/3337/2026/8109310.pdf",
      "nomeFornecedor": "A3 Serviços de Publicidade e Comunicação LTDA",
      "cnpjCpfFornecedor": "32433119000144",
      "valorLiquido": 6000.0,
      "valorGlosa": 0.0,
      "numRessarcimento": "",
      "codLote": 2241058,
      "parcela": 0
    }
  ],
  "links": [
    {
      "rel": "self",
      "href": "https://dadosabertos.camara.leg.br/api/v2/deputados/204459/despesas?ano=2026&mes=5&ordem=ASC&ordenarPor=ano&itens=100&pagina=1"
    },
    {
      "rel": "first",
      "href": "https://dadosabertos.camara.leg.br/api/v2/deputados/204459/despesas?ano=2026&mes=5&ordem=ASC&ordenarPor=ano&pagina=1&itens=100"
    },
    {
      "rel": "last",
      "href": "https://dadosabertos.camara.leg.br/api/v2/deputados/204459/despesas?ano=2026&mes=5&ordem=ASC&ordenarPor=ano&pagina=1&itens=100"
    }
  ]
}