{
  "dados": [
    {
      "ano": 2026,
      "mes": 5,
      "tipoDespesa": "MANUTENÇÃO DE ESCRITÓRIO DE APOIO À ATIVIDADE PARLAMENTAR",
      "codDocumento": "8107670",
      "tipoDocumento": "Nota Fiscal",
      "codTipoDocumento": 0,
      "dataDocumento": "2026-05-14T00:00:00",
      "numDocumento": "962188444",
      "valorDocumento": 1238.0,
      "urlDocumento": "https://www.camara.leg.br/cota-parlamentar/documentos/publ/2938/2026/8107670.pdf",
      "nomeFornecedor": "COMPANHIA DE ELETRICIDADE DO ESTADO DA BAHIA",
      "cnpjCpfFornecedor": "15139629000194",
      "valorLiquido": 1036.07,
      "valorGlosa": 201.93,
      "numRessarcimento": "",
      "codLote": 2240574,
      "parcela": 0
    },
    {
      "ano": 2026,
      "mes": 5,
      "tipoDespesa": "MANUTENÇÃO DE ESCRITÓRIO DE APOIO À ATIVIDADE PARLAMENTAR",
      "codDocumento": "8098741",
      "tipoDocumento": "Recibos/Outros",
      "codTipoDocumento": 1,
      "dataDocumento": "2026-05-05T00:00:00",
      "numDocumento": "s/n",
      "valorDocumento": 2559.02,
      "urlDocumento": "https://www.camara.leg.br/cota-parlamentar/documentos/publ/2938/2026/8098741.pdf",
      "nomeFornecedor": "INFORMATICA EMPREENDIMENTOS IMOBILIARIOS LTDA",
      "cnpjCpfFornecedor": "14997688000130",
      "valorLiquido": 2559.02,
      "valorGlosa": 0.0,
      "numRessarcimento": "",
      "codLote": 2235514,
      "parcela": 0
    },
    {
      "ano": 2026,
      "mes": 5,
      "tipoDespesa": "MANUTENÇÃO DE ESCRITÓRIO DE APOIO À ATIVIDADE PARLAMENTAR",
      "codDocumento": "8098743",
      "tipoDocumento": "Recibos/Outros",
      "codTipoDocumento": 1,
      "dataDocumento": "2026-05-05T00:00:00",
      "numDocumento": "s/n",
      "valorDocumento": 2559.02,
      "urlDocumento": "https://www.camara.leg.br/cota-parlamentar/documentos/publ/2938/2026/8098743.pdf",
      "nomeFornecedor": "INFORMATICA EMPREENDIMENTOS IMOBILIARIOS LTDA",
      "cnpjCpfFornecedor": "14997688000130",
      "valorLiquido": 2559.02,
      "valorGlosa": 0.0,
      "numRessarcimento": "",
      "codLote": 2235514,
      "parcela": 0
    },
    {
      "ano": 2026,
      "mes": 5,
      "tipoDespesa": "MANUTENÇÃO DE ESCRITÓRIO DE APOIO À ATIVIDADE PARLAMENTAR",
      "codDocumento": "8098742",
      "tipoDocumento": "Recibos/Outros",
      "codTipoDocumento": 1,
      "dataDocumento": "2026-05-05T00:00:00",
      "numDocumento": "s/n",
      "valorDocumento": 2742.66,
      "urlDocumento": "https://www.camara.leg.br/cota-parlamentar/documentos/publ/2938/2026/8098742.pdf",
      "nomeFornecedor": "INFORMATICA EMPREENDIMENTOS IMOBILIARIOS LTDA",
      "cnpjCpfFornecedor": "14997688000130",
      "valorLiquido": 2742.66,
      "valorGlosa": 0.0,
      "numRessarcimento": "",
      "codLote": 2235514,
      "parcela": 0
    },
    {
      "ano": 2026,
      "mes": 5,
      "tipoDespesa": "COMBUSTÍVEIS E LUBRIFICANTES.",
      "codDocumento": "8129655",
      "tipoDocumento": "Nota Fiscal Eletrônica",
      "codTipoDocumento": 4,
      "dataDocumento": "2026-05-25T00:00:00",
      "numDocumento": "4693",
      "valorDocumento": 470.6,
      "urlDocumento": "http://www.camara.leg.br/cota-parlamentar/nota-fiscal-eletronica?ideDocumentoFiscal=8129655",
      "nomeFornecedor": "3L COMERCIO DE COMBUSTIVEIS E LUBRIFICANTES LTDA.",
      "cnpjCpfFornecedor": "07192452000161",
      "valorLiquido": 390.61,
      "valorGlosa": 79.99,
      "numRessarcimento": "",
      "codLote": 2251376,
      "parcela": 0
    },
    {
      "ano": 2026,
      "mes": 5,
      "tipoDespesa": "COMBUSTÍVEIS E LUBRIFICANTES.",
      "codDocumento": "8116518",
      "tipoDocumento": "Nota Fiscal Eletrônica",
      "codTipoDocumento": 4,
      "dataDocumento": "2026-05-17T16:01:12",
      "numDocumento": "745435",
      "valorDocumento": 467.05,
      "urlDocumento": "http://www.camara.leg.br/cota-parlamentar/nota-fiscal-eletronica?ideDocumentoFiscal=8116518",
      "nomeFornecedor": "AF ANDRADE COMERCIO DE COMBUSTIVEIS LTDA - EPP",
      "cnpjCpfFornecedor": "26304064000170",
      "valorLiquido": 467.05,
      "valorGlosa": 0.0,
      "numRessarcimento": "",
      "codLote": 2245434,
      "parcela": 0
    },
    {
      "ano": 2026,
      "mes": 5,
      "tipoDespesa": "COMBUSTÍVEIS E LUBRIFICANTES.",
      "codDocumento": "8129656",
      "tipoDocumento": "Nota Fiscal Eletrônica",
      "codTipoDocumento": 4,
      "dataDocumento": "2026-05-29T09:52:13",
      "numDocumento": "278703",
      "valorDocumento": 520.15,
      "urlDocumento": "http://www.camara.leg.br/cota-parlamentar/nota-fiscal-eletronica?ideDocumentoFiscal=8129656",
      "nomeFornecedor": "AMN DERIVADOS DO PETROLEO E TRANSPORTES EIRELI-ME",
      "cnpjCpfFornecedor": "25198095000120",
      "valorLiquido": 157.68,
      "valorGlosa": 362.47,
      "numRessarcimento": "",
      "codLote": 2251376,
      "parcela": 0
    },
    {
      "ano": 2026,
      "mes": 5,
      "tipoDespesa": "COMBUSTÍVEIS E LUBRIFICANTES.",
      "codDocumento": "8129646",
      "tipoDocumento": "Nota Fiscal Eletrônica",
      "codTipoDocumento": 4,
      "dataDocumento": "2026-05-07T17:19:35",
      "numDocumento": "863497",
      "valorDocumento": 200.0,
      "urlDocumento": "http://www.camara.leg.br/cota-parlamentar/nota-fiscal-eletronica?ideDocumentoFiscal=8129646",
      "nomeFornecedor": "AUTO POSTO CAMURUPIM LTDA",
      "cnpjCpfFornecedor": "06895357000161",
      "valorLiquido": 200.0,
      "valorGlosa": 0.0,
      "numRessarcimento": "",
      "codLote": 2251376,
      "parcela": 0
    },
    {
      "ano": 2026,
      "mes": 5,
      "tipoDespesa": "COMBUSTÍVEIS E LUBRIFICANTES.",
      "codDocumento": "8098736",
      "tipoDocumento": "Nota Fiscal Eletrônica",
      "codTipoDocumento": 4,
      "dataDocumento": "2026-05-10T21:23:39",
      "numDocumento": "2334669",
      "valorDocumento": 202.31,
      "urlDocumento": "http://www.camara.leg.br/cota-parlamentar/nota-fiscal-eletronica?ideDocumentoFiscal=8098736",
      "nomeFornecedor": "CARLOS EDUARDO CASAGRANDE",
      "cnpjCpfFornecedor": "12233356000154",
      "valorLiquido": 202.31,
      "valorGlosa": 0.0,
      "numRessarcimento": "",
      "codLote": 2235515,
      "parcela": 0
    },
    {
      "ano": 2026,
      "mes": 5,
      "tipoDespesa": "COMBUSTÍVEIS E LUBRIFICANTES.",
      "codDocumento": "8129644",
      "tipoDocumento": "Nota Fiscal Eletrônica",
      "codTipoDocumento": 4,
      "dataDocumento": "2026-05-20T19:37:46",
      "numDocumento": "862673",
      "valorDocumento": 100.0,
      "urlDocumento": "http://www.camara.leg.br/cota-parlamentar/nota-fiscal-eletronica?ideDocumentoFiscal=8129644",
      "nomeFornecedor": "CATEGORIA  ECOPOSTOS COMBUSTIVEIS E SERVICOS LTDA",
      "cnpjCpfFornecedor": "04420464000370",
      "valorLiquido": 100.0,
      "valorGlosa": 0.0,
      "numRessarcimento": "",
      "codLote": 2251376,
      "parcela": 0
    },
    {
      "ano": 2026,
      "mes": 5,
      "tipoDespesa": "COMBUSTÍVEIS E LUBRIFICANTES.",
      "codDocumento": "8098733",
      "tipoDocumento": "Nota Fiscal Eletrônica",
      "codTipoDocumento": 4,
      "dataDocumento": "2026-05-11T00:00:00",
      "numDocumento": "958866",
      "valorDocumento": 473.21,
      "urlDocumento": "http://www.camara.leg.br/cota-parlamentar/nota-fiscal-eletronica?ideDocumentoFiscal=8098733",
      "nomeFornecedor": "COMERCIAL DE COMBUSTIVEIS CIDADE JARDIM LTDA",
      "cnpjCpfFornecedor": "02377962000190",
      "valorLiquido": 473.21,
      "valorGlosa": 0.0,
      "numRessarcimento": "",
      "codLote": 2235515,
      "parcela": 0
    },
    {
      "ano": 2026,
      "mes": 5,
      "tipoDespesa": "COMBUSTÍVEIS E LUBRIFICANTES.",
      "codDocumento": "8129643",
      "tipoDocumento": "Nota Fiscal Eletrônica",
      "codTipoDocumento": 4,
      "dataDocumento": "2026-05-14T00:00:00",
      "numDocumento": "960189",
      "valorDocumento": 100.0,
      "urlDocumento": "http://www.camara.leg.br/cota-parlamentar/nota-fiscal-eletronica?ideDocumentoFiscal=8129643",
      "nomeFornecedor": "COMERCIAL DE COMBUSTIVEIS CIDADE JARDIM LTDA",
      "cnpjCpfFornecedor": "02377962000190",
      "valorLiquido": 100.0,
      "valorGlosa": 0.0,
      "numRessarcimento": "",
      "codLote": 2251376,
      "parcela": 0
    },
    {
      "ano": 2026,
      "mes": 5,
      "tipoDespesa": "COMBUSTÍVEIS E LUBRIFICANTES.",
      "codDocumento": "8098738",
      "tipoDocumento": "Nota Fiscal Eletrônica",
      "codTipoDocumento": 4,
      "dataDocumento": "2026-05-01T00:00:00",
      "numDocumento": "33911",
      "valorDocumento": 218.65,
      "urlDocumento": "http://www.camara.leg.br/cota-parlamentar/nota-fiscal-eletronica?ideDocumentoFiscal=8098738",
      "nomeFornecedor": "DERIVADOS DE PETROLEO MAR GRANDE",
      "cnpjCpfFornecedor": "55155127000171",
      "valorLiquido": 218.65,
      "valorGlosa": 0.0,
      "numRessarcimento": "",
      "codLote": 2235515,
      "parcela": 0
    },
    {
      "ano": 2026,
      "mes": 5,
      "tipoDespesa": "COMBUSTÍVEIS E LUBRIFICANTES.",
      "codDocumento": "8116499",
      "tipoDocumento": "Nota Fiscal Eletrônica",
      "codTipoDocumento": 4,
      "dataDocumento": "2026-05-28T08:24:04",
      "numDocumento": "2468862",
      "valorDocumento": 100.0,
      "urlDocumento": "http://www.camara.leg.br/cota-parlamentar/nota-fiscal-eletronica?ideDocumentoFiscal=8116499",
      "nomeFornecedor": "DEUSREI - COMBUSTIVEIS E LUBRIFICANTES LTDA",
      "cnpjCpfFornecedor": "05643704000104",
      "valorLiquido": 100.0,
      "valorGlosa": 0.0,
      "numRessarcimento": "",
      "codLote": 2245434,
      "parcela": 0
    },
    {
      "ano": 2026,
      "mes": 5,
      "tipoDespesa": "COMBUSTÍVEIS E LUBRIFICANTES.",
      "codDocumento": "8116511",
      "tipoDocumento": "Nota Fiscal Eletrônica",
      "codTipoDocumento": 4,
      "dataDocumento": "2026-05-14T17:07:40",
      "numDocumento": "656536",
      "valorDocumento": 515.78,
      "urlDocumento": "http://www.camara.leg.br/cota-parlamentar/nota-fiscal-eletronica?ideDocumentoFiscal=8116511",
      "nomeFornecedor": "HP COMERCIO E DERIVADOS DE PETROLEO LTDA",
      "cnpjCpfFornecedor": "02818012000404",
      "valorLiquido": 515.78,
      "valorGlosa": 0.0,
      "numRessarcimento": "",
      "codLote": 2245434,
      "parcela": 0
    },
    {
      "ano": 2026,
      "mes": 5,
      "tipoDespesa": "COMBUSTÍVEIS E LUBRIFICANTES.",
      "codDocumento": "8107511",
      "tipoDocumento": "Nota Fiscal Eletrônica",
      "codTipoDocumento": 4,
      "dataDocumento": "2026-05-21T00:00:00",
      "numDocumento": "16441",
      "valorDocumento": 271.79,
      "urlDocumento": "http://www.camara.leg.br/cota-parlamentar/nota-fiscal-eletronica?ideDocumentoFiscal=8107511",
      "nomeFornecedor": "HZL COMERCIAL DE COMBUSTIVEL LTDA",
      "cnpjCpfFornecedor": "51560245000104",
      "valorLiquido": 271.79,
      "valorGlosa": 0.0,
      "numRessarcimento": "",
      "codLote": 2240576,
      "parcela": 0
    },
    {
      "ano": 2026,
      "mes": 5,
      "tipoDespesa": "COMBUSTÍVEIS E LUBRIFICANTES.",
      "codDocumento": "8107499",
      "tipoDocumento": "Nota Fiscal Eletrônica",
      "codTipoDocumento": 4,
      "dataDocumento": "2026-05-24T00:00:00",
      "numDocumento": "7022",
      "valorDocumento": 242.05,
      "urlDocumento": "http://www.camara.leg.br/cota-parlamentar/nota-fiscal-eletronica?ideDocumentoFiscal=8107499",
      "nomeFornecedor": "J. PETRO COMERCIO DE COMBUSTIVEIS E LUBRIFICANTES LTDA",
      "cnpjCpfFornecedor": "31713774000193",
      "valorLiquido": 242.05,
      "valorGlosa": 0.0,
      "numRessarcimento": "",
      "codLote": 2240576,
      "parcela": 0
    },
    {
      "ano": 2026,
      "mes": 5,
      "tipoDespesa": "COMBUSTÍVEIS E LUBRIFICANTES.",
      "codDocumento": "8095469",
      "tipoDocumento": "Nota Fiscal Eletrônica",
      "codTipoDocumento": 4,
      "dataDocumento": "2026-05-02T00:00:00",
      "numDocumento": "148607",
      "valorDocumento": 479.24,
      "urlDocumento": "http://www.camara.leg.br/cota-parlamentar/nota-fiscal-eletronica?ideDocumentoFiscal=8095469",
      "nomeFornecedor": "MARIA JOSENILDA SILVA DE MACEDO",
      "cnpjCpfFornecedor": "07399912000399",
      "valorLiquido": 479.24,
      "valorGlosa": 0.0,
      "numRessarcimento": "",
      "codLote": 2233684,
      "parcela": 0
    },
    {
      "ano": 2026,
      "mes": 5,
      "tipoDespesa": "COMBUSTÍVEIS E LUBRIFICANTES.",
      "codDocumento": "8116523",
      "tipoDocumento": "Nota Fiscal Eletrônica",
      "codTipoDocumento": 4,
      "dataDocumento": "2026-05-14T20:07:39",
      "numDocumento": "1811205",
      "valorDocumento": 200.0,
      "urlDocumento": "http://www.camara.leg.br/cota-parlamentar/nota-fiscal-eletronica?ideDocumentoFiscal=8116523",
      "nomeFornecedor": "MICRO POSTO RIO VERMELHO LTDA",
      "cnpjCpfFornecedor": "14889497000155",
      "valorLiquido": 200.0,
      "valorGlosa": 0.0,
      "numRessarcimento": "",
      "codLote": 2245434,
      "parcela": 0
    },
    {
      "ano": 2026,
      "mes": 5,
      "tipoDespesa": "COMBUSTÍVEIS E LUBRIFICANTES.",
      "codDocumento": "8117517",
      "tipoDocumento": "Nota Fiscal Eletrônica",
      "codTipoDocumento": 4,
      "dataDocumento": "2026-05-08T00:00:00",
      "numDocumento": "220466",
      "valorDocumento": 262.43,
      "urlDocumento": "http://www.camara.leg.br/cota-parlamentar/nota-fiscal-eletronica?ideDocumentoFiscal=8117517",
      "nomeFornecedor": "MP COMERCIO DE COMBUSTIVEIS LTDA",
      "cnpjCpfFornecedor": "09149936000315",
      "valorLiquido": 262.43,
      "valorGlosa": 0.0,
      "numRessarcimento": "",
      "codLote": 2245434,
      "parcela": 0
    },
    {
      "ano": 2026,
      "mes": 5,
      "tipoDespesa": "COMBUSTÍVEIS E LUBRIFICANTES.",
      "codDocumento": "8093497",
      "tipoDocumento": "Nota Fiscal",
      "codTipoDocumento": 0,
      "dataDocumento": "2026-05-04T00:00:00",
      "numDocumento": "2316",
      "valorDocumento": 1000.0,
      "urlDocumento": "https://www.camara.leg.br/cota-parlamentar/documentos/publ/2938/2026/8093497.pdf",
      "nomeFornecedor": "PETROFLEX COMERCIO E SERVICOS LTDA  EPP",
      "cnpjCpfFornecedor": "07969541000171",
      "valorLiquido": 1000.0,
      "valorGlosa": 0.0,
      "numRessarcimento": "",
      "codLote": 2232586,
      "parcela": 0
    },
    {
      "ano": 2026,
      "mes": 5,
      "tipoDespesa": "COMBUSTÍVEIS E LUBRIFICANTES.",
      "codDocumento": "8116526",
      "tipoDocumento": "Nota Fiscal Eletrônica",
      "codTipoDocumento": 4,
      "dataDocumento": "2026-05-18T05:38:02",
      "numDocumento": "510177",
      "valorDocumento": 285.04,
      "urlDocumento": "http://www.camara.leg.br/cota-parlamentar/nota-fiscal-eletronica?ideDocumentoFiscal=8116526",
      "nomeFornecedor": "PETROMERC DERIVADOS DE PETROLEO LTDA",
      "cnpjCpfFornecedor": "03562365000289",
      "valorLiquido": 285.04,
      "valorGlosa": 0.0,
      "numRessarcimento": "",
      "codLote": 2245434,
      "parcela": 0
    },
    {
      "ano": 2026,
      "mes": 5,
      "tipoDespesa": "COMBUSTÍVEIS E LUBRIFICANTES.",
      "codDocumento": "8116517",
      "tipoDocumento": "Nota Fiscal Eletrônica",
      "codTipoDocumento": 4,
      "dataDocumento": "2026-05-16T17:09:02",
      "numDocumento": "6616",
      "valorDocumento": 509.99,
      "urlDocumento": "http://www.camara.leg.br/cota-parlamentar/nota-fiscal-eletronica?ideDocumentoFiscal=8116517",
      "nomeFornecedor": "PGS TANQUINHO BAHIA COMBUSTIVEIS LTDA",
      "cnpjCpfFornecedor": "45904896000171",
      "valorLiquido": 509.99,
      "valorGlosa": 0.0,
      "numRessarcimento": "",
      "codLote": 2245434,
      "parcela": 0
    },
    {
      "ano": 2026,
      "mes": 5,
      "tipoDespesa": "COMBUSTÍVEIS E LUBRIFICANTES.",
      "codDocumento": "8129645",
      "tipoDocumento": "Nota Fiscal Eletrônica",
      "codTipoDocumento": 4,
      "dataDocumento": "2026-05-06T00:00:00",
      "numDocumento": "366261",
      "valorDocumento": 100.0,
      "urlDocumento": "http://www.camara.leg.br/cota-parlamentar/nota-fiscal-eletronica?ideDocumentoFiscal=8129645",
      "nomeFornecedor": "PNH COMERCIO DE COMBUSTIVEIS LTDA",
      "cnpjCpfFornecedor": "28079099000188",
      "valorLiquido": 100.0,
      "valorGlosa": 0.0,
      "numRessarcimento": "",
      "codLote": 2251376,
      "parcela": 0
    },
    {
      "ano": 2026,
      "mes": 5,
      "tipoDespesa": "COMBUSTÍVEIS E LUBRIFICANTES.",
      "codDocumento": "8107505",
      "tipoDocumento": "Nota Fiscal Eletrônica",
      "codTipoDocumento": 4,
      "dataDocumento": "2026-05-24T00:00:00",
      "numDocumento": "420834",
      "valorDocumento": 212.08,
      "urlDocumento": "http://www.camara.leg.br/cota-parlamentar/nota-fiscal-eletronica?ideDocumentoFiscal=8107505",
      "nomeFornecedor": "POSTO CIDADE DE BRUMADO LTDA",
      "cnpjCpfFornecedor": "10646673000177",
      "valorLiquido": 212.08,
      "valorGlosa": 0.0,
      "numRessarcimento": "",
      "codLote": 2240576,
      "parcela": 0
    },
    {
      "ano": 2026,
      "mes": 5,
      "tipoDespesa": "COMBUSTÍVEIS E LUBRIFICANTES.",
      "codDocumento": "8129653",
      "tipoDocumento": "Nota Fiscal Eletrônica",
      "codTipoDocumento": 4,
      "dataDocumento": "2026-05-25T12:26:32",
      "numDocumento": "1130428",
      "valorDocumento": 280.04,
      "urlDocumento": "http://www.camara.leg.br/cota-parlamentar/nota-fiscal-eletronica?ideDocumentoFiscal=8129653",
      "nomeFornecedor": "POSTO GUANAMBI LTDA",
      "cnpjCpfFornecedor": "42149328000114",
      "valorLiquido": 280.04,
      "valorGlosa": 0.0,
      "numRessarcimento": "",
      "codLote": 2251376,
      "parcela": 0
    },
    {
      "ano": 2026,
      "mes": 5,
      "tipoDespesa": "COMBUSTÍVEIS E LUBRIFICANTES.",
      "codDocumento": "8116522",
      "tipoDocumento": "Nota Fiscal Eletrônica",
      "codTipoDocumento": 4,
      "dataDocumento": "2026-05-09T08:41:20",
      "numDocumento": "216998",
      "valorDocumento": 288.59,
      "urlDocumento": "http://www.camara.leg.br/cota-parlamentar/nota-fiscal-eletronica?ideDocumentoFiscal=8116522",
      "nomeFornecedor": "POSTO ILPRES COM DE COMBUSTIVEIS E LUB LTDA",
      "cnpjCpfFornecedor": "10905163000177",
      "valorLiquido": 288.59,
      "valorGlosa": 0.0,
      "numRessarcimento": "",
      "codLote": 2245434,
      "parcela": 0
    },
    {
      "ano": 2026,
      "mes": 5,
      "tipoDespesa": "COMBUSTÍVEIS E LUBRIFICANTES.",
      "codDocumento": "8107523",
      "tipoDocumento": "Nota Fiscal Eletrônica",
      "codTipoDocumento": 4,
      "dataDocumento": "2026-05-23T00:00:00",
      "numDocumento": "784974",
      "valorDocumento": 322.07,
      "urlDocumento": "http://www.camara.leg.br/cota-parlamentar/nota-fiscal-eletronica?ideDocumentoFiscal=8107523",
      "nomeFornecedor": "POSTO MACAUBENSE LTDA",
      "cnpjCpfFornecedor": "40605115000124",
      "valorLiquido": 322.07,
      "valorGlosa": 0.0,
      "numRessarcimento": "",
      "codLote": 2240576,
      "parcela": 0
    },
    {
      "ano": 2026,
      "mes": 5,
      "tipoDespesa": "COMBUSTÍVEIS E LUBRIFICANTES.",
      "codDocumento": "8116512",
      "tipoDocumento": "Nota Fiscal Eletrônica",
      "codTipoDocumento": 4,
      "dataDocumento": "2026-05-15T00:00:00",
      "numDocumento": "517452",
      "valorDocumento": 687.14,
      "urlDocumento": "http://www.camara.leg.br/cota-parlamentar/nota-fiscal-eletronica?ideDocumentoFiscal=8116512",
      "nomeFornecedor": "REPROPEL REVEN DE PROD DE PETRO LTDA",
      "cnpjCpfFornecedor": "01607879000105",
      "valorLiquido": 596.54,
      "valorGlosa": 90.6,
      "numRessarcimento": "",
      "codLote": 2245434,
      "parcela": 0
    },
    {
      "ano": 2026,
      "mes": 5,
      "tipoDespesa": "COMBUSTÍVEIS E LUBRIFICANTES.",
      "codDocumento": "8107518",
      "tipoDocumento": "Nota Fiscal Eletrônica",
      "codTipoDocumento": 4,
      "dataDocumento": "2026-05-20T00:00:00",
      "numDocumento": "310744",
      "valorDocumento": 230.02,
      "urlDocumento": "http://www.camara.leg.br/cota-parlamentar/nota-fiscal-eletronica?ideDocumentoFiscal=8107518",
      "nomeFornecedor": "SODIC SOCIEDADE REVENDEDORA DE COMBUSTIVEIS LTDA",
      "cnpjCpfFornecedor": "15847874000318",
      "valorLiquido": 230.02,
      "valorGlosa": 0.0,
      "numRessarcimento": "",
      "codLote": 2240576,
      "parcela": 0
    },
    {
      "ano": 2026,
      "mes": 5,
      "tipoDespesa": "COMBUSTÍVEIS E LUBRIFICANTES.",
      "codDocumento": "8095463",
      "tipoDocumento": "Nota Fiscal Eletrônica",
      "codTipoDocumento": 4,
      "dataDocumento": "2026-05-02T21:03:26",
      "numDocumento": "1986334",
      "valorDocumento": 275.67,
      "urlDocumento": "http://www.camara.leg.br/cota-parlamentar/nota-fiscal-eletronica?ideDocumentoFiscal=8095463",
      "nomeFornecedor": "SRB REVENDEDORA DE COMBUSTIVEIS E LUBRIFICANTES LTDA",
      "cnpjCpfFornecedor": "08091287000114",
      "valorLiquido": 275.67,
      "valorGlosa": 0.0,
      "numRessarcimento": "",
      "codLote": 2233684,
      "parcela": 0
    },
    {
      "ano": 2026,
      "mes": 5,
      "tipoDespesa": "COMBUSTÍVEIS E LUBRIFICANTES.",
      "codDocumento": "8095411",
      "tipoDocumento": "Nota Fiscal Eletrônica",
      "codTipoDocumento": 4,
      "dataDocumento": "2026-05-04T19:07:19",
      "numDocumento": "1987395",
      "valorDocumento": 300.08,
      "urlDocumento": "http://www.camara.leg.br/cota-parlamentar/nota-fiscal-eletronica?ideDocumentoFiscal=8095411",
      "nomeFornecedor": "SRB REVENDEDORA DE COMBUSTIVEIS E LUBRIFICANTES LTDA",
      "cnpjCpfFornecedor": "08091287000114",
      "valorLiquido": 300.08,
      "valorGlosa": 0.0,
      "numRessarcimento": "",
      "codLote": 2233684,
      "parcela": 0
    },
    {
      "ano": 2026,
      "mes": 5,
      "tipoDespesa": "COMBUSTÍVEIS E LUBRIFICANTES.",
      "codDocumento": "8117516",
      "tipoDocumento": "Nota Fiscal Eletrônica",
      "codTipoDocumento": 4,
      "dataDocumento": "2026-05-04T18:58:29",
      "numDocumento": "604476",
      "valorDocumento": 511.08,
      "urlDocumento": "http://www.camara.leg.br/cota-parlamentar/nota-fiscal-eletronica?ideDocumentoFiscal=8117516",
      "nomeFornecedor": "TOURING  ECOPOSTOS COMBUSTIVEIS E SERVICOS LTDA",
      "cnpjCpfFornecedor": "04420464000299",
      "valorLiquido": 511.08,
      "valorGlosa": 0.0,
      "numRessarcimento": "",
      "codLote": 2245434,
      "parcela": 0
    },
    {
      "ano": 2026,
      "mes": 5,
      "tipoDespesa": "COMBUSTÍVEIS E LUBRIFICANTES.",
      "codDocumento": "8129650",
      "tipoDocumento": "Nota Fiscal Eletrônica",
      "codTipoDocumento": 4,
      "dataDocumento": "2026-05-29T00:00:00",
      "numDocumento": "189953",
      "valorDocumento": 100.0,
      "urlDocumento": "http://www.camara.leg.br/cota-parlamentar/nota-fiscal-eletronica?ideDocumentoFiscal=8129650",
      "nomeFornecedor": "WF COMERCIO DE COMBUSTIVEIS E SERVICOS LTDA",
      "cnpjCpfFornecedor": "18317568000104",
      "valorLiquido": 100.0,
      "valorGlosa": 0.0,
      "numRessarcimento": "",
      "codLote": 2251376,
      "parcela": 0
    },
    {
      "ano": 2026,
      "mes": 5,
      "tipoDespesa": "DIVULGAÇÃO DA ATIVIDADE PARLAMENTAR.",
      "codDocumento": "8107418",
      "tipoDocumento": "Nota Fiscal",
      "codTipoDocumento": 0,
      "dataDocumento": "2026-05-26T00:00:00",
      "numDocumento": "00000006",
      "valorDocumento": 3500.0,
      "urlDocumento": "https://www.camara.leg.br/cota-parlamentar/documentos/publ/2938/2026/8107418.pdf",
      "nomeFornecedor": "LARA SOFIA ROCHA MENDES DA SILVA LTDA",
      "cnpjCpfFornecedor": "60553261000160",
      "valorLiquido": 3500.0,
      "valorGlosa": 0.0,
      "numRessarcimento": "",
      "codLote": 2240575,
      "parcela": 0
    },
    {
      "ano": 2026,
      "mes": 5,
      "tipoDespesa": "DIVULGAÇÃO DA ATIVIDADE PARLAMENTAR.",
      "codDocumento": "8117405",
      "tipoDocumento": "Nota Fiscal",
      "codTipoDocumento": 0,
      "dataDocumento": "2026-05-22T00:00:00",
      "numDocumento": "173",
      "valorDocumento": 3000.0,
      "urlDocumento": "https://www.camara.leg.br/cota-parlamentar/documentos/publ/2938/2026/8117405.pdf",
      "nomeFornecedor": "ROMULO CARVALHO FONTOURA - ME",
      "cnpjCpfFornecedor": "17188789000159",
      "valorLiquido": 3000.0,
      "valorGlosa": 0.0,
      "numRessarcimento": "",
      "codLote": 2245433,
      "parcela": 0
    },
    {
      "ano": 2026,
      "mes": 5,
      "tipoDespesa": "TELEFONIA",
      "codDocumento": "8106620",
      "tipoDocumento": "Nota Fiscal",
      "codTipoDocumento": 0,
      "dataDocumento": "2026-05-13T00:00:00",
      "numDocumento": "10789501",
      "valorDocumento": 171.0,
      "urlDocumento": null,
      "nomeFornecedor": "TELEFONICA BRASIL S/A - VIVO",
      "cnpjCpfFornecedor": "02558157000162",
      "valorLiquido": 171.0,
      "valorGlosa": 0.0,
      "numRessarcimento": "",
      "codLote": 2240574,
      "parcela": 0
    },
    {
      "ano": 2026,
      "mes": 5,
      "tipoDespesa": "FORNECIMENTO DE ALIMENTAÇÃO DO PARLAMENTAR",
      "codDocumento": "8116498",
      "tipoDocumento": "Nota Fiscal Eletrônica",
      "codTipoDocumento": 4,
      "dataDocumento": "2026-05-16T00:00:00",
      "numDocumento": "66448",
      "valorDocumento": 40.99,
      "urlDocumento": "http://www.camara.leg.br/cota-parlamentar/nota-fiscal-eletronica?ideDocumentoFiscal=8116498",
      "nomeFornecedor": "DAVI BARBOSA PAIM PEREIRA",
      "cnpjCpfFornecedor": "29815786000187",
      "valorLiquido": 40.99,
      "valorGlosa": 0.0,
      "numRessarcimento": "",
      "codLote": 2245435,
      "parcela": 0
    },
    {
      "ano": 2026,
      "mes": 5,
      "tipoDespesa": "FORNECIMENTO DE ALIMENTAÇÃO DO PARLAMENTAR",
      "codDocumento": "8116505",
      "tipoDocumento": "Nota Fiscal Eletrônica",
      "codTipoDocumento": 4,
      "dataDocumento": "2026-05-15T00:00:00",
      "numDocumento": "562234",
      "valorDocumento": 94.9,
      "urlDocumento": "http://www.camara.leg.br/cota-parlamentar/nota-fiscal-eletronica?ideDocumentoFiscal=8116505",
      "nomeFornecedor": "LANCHONETE E RESTAURANTE ACACIA LTDA",
      "cnpjCpfFornecedor": "03130640000104",
      "valorLiquido": 94.9,
      "valorGlosa": 0.0,
      "numRessarcimento": "",
      "codLote": 2245435,
      "parcela": 0
    },
    {
      "ano": 2026,
      "mes": 5,
      "tipoDespesa": "FORNECIMENTO DE ALIMENTAÇÃO DO PARLAMENTAR",
      "codDocumento": "8116504",
      "tipoDocumento": "Nota Fiscal Eletrônica",
      "codTipoDocumento": 4,
      "dataDocumento": "2026-05-16T00:00:00",
      "numDocumento": "12668",
      "valorDocumento": 96.0,
      "urlDocumento": "http://www.camara.leg.br/cota-parlamentar/nota-fiscal-eletronica?ideDocumentoFiscal=8116504",
      "nomeFornecedor": "RESTAURANTE LANCHONETE E POUSADA DO DIDI LTDA",
      "cnpjCpfFornecedor": "11670823000140",
      "valorLiquido": 96.0,
      "valorGlosa": 0.0,
      "numRessarcimento": "",
      "codLote": 2245435,
      "parcela": 0
    },
    {
      "ano": 2026,
      "mes": 5,
      "tipoDespesa": "FORNECIMENTO DE ALIMENTAÇÃO DO PARLAMENTAR",
      "codDocumento": "8117479",
      "tipoDocumento": "Nota Fiscal Eletrônica",
      "codTipoDocumento": 4,
      "dataDocumento": "2026-05-08T00:00:00",
      "numDocumento": "6668",
      "valorDocumento": 75.85,
      "urlDocumento": "http://www.camara.leg.br/cota-parlamentar/nota-fiscal-eletronica?ideDocumentoFiscal=8117479",
      "nomeFornecedor": "S F RESTAURANTE LTDA",
      "cnpjCpfFornecedor": "29414896000137",
      "valorLiquido": 75.85,
      "valorGlosa": 0.0,
      "numRessarcimento": "",
      "codLote": 2245435,
      "parcela": 0
    },
    {
      "ano": 2026,
      "mes": 5,
      "tipoDespesa": "FORNECIMENTO DE ALIMENTAÇÃO DO PARLAMENTAR",
      "codDocumento": "8116508",
      "tipoDocumento": "Nota Fiscal Eletrônica",
      "codTipoDocumento": 4,
      "dataDocumento": "2026-05-13T00:00:00",
      "numDocumento": "202",
      "valorDocumento": 57.84,
      "urlDocumento": "http://www.camara.leg.br/cota-parlamentar/nota-fiscal-eletronica?ideDocumentoFiscal=8116508",
      "nomeFornecedor": "SERVICO NACIONAL DE APREND. COMERCIAL",
      "cnpjCpfFornecedor": "33469172000672",
      "valorLiquido": 57.84,
      "valorGlosa": 0.0,
      "numRessarcimento": "",
      "codLote": 2245435,
      "parcela": 0
    },
    {
      "ano": 2026,
      "mes": 5,
      "tipoDespesa": "FORNECIMENTO DE ALIMENTAÇÃO DO PARLAMENTAR",
      "codDocumento": "8116507",
      "tipoDocumento": "Nota Fiscal Eletrônica",
      "codTipoDocumento": 4,
      "dataDocumento": "2026-05-12T00:00:00",
      "numDocumento": "3406",
      "valorDocumento": 55.0,
      "urlDocumento": "http://www.camara.leg.br/cota-parlamentar/nota-fiscal-eletronica?ideDocumentoFiscal=8116507",
      "nomeFornecedor": "SERVICO NACIONAL DE APREND. COMERCIAL",
      "cnpjCpfFornecedor": "33469172001644",
      "valorLiquido": 55.0,
      "valorGlosa": 0.0,
      "numRessarcimento": "",
      "codLote": 2245435,
      "parcela": 0
    },
    {
      "ano": 2026,
      "mes": 5,
      "tipoDespesa": "FORNECIMENTO DE ALIMENTAÇÃO DO PARLAMENTAR",
      "codDocumento": "8116510",
      "tipoDocumento": "Nota Fiscal Eletrônica",
      "codTipoDocumento": 4,
      "dataDocumento": "2026-05-13T00:00:00",
      "numDocumento": "532642",
      "valorDocumento": 17.99,
      "urlDocumento": "http://www.camara.leg.br/cota-parlamentar/nota-fiscal-eletronica?ideDocumentoFiscal=8116510",
      "nomeFornecedor": "TAIOBA SELF-SERVICE LTDA EPP",
      "cnpjCpfFornecedor": "03346671001330",
      "valorLiquido": 17.99,
      "valorGlosa": 0.0,
      "numRessarcimento": "",
      "codLote": 2245435,
      "parcela": 0
    },
    {
      "ano": 2026,
      "mes": 5,
      "tipoDespesa": "FORNECIMENTO DE ALIMENTAÇÃO DO PARLAMENTAR",
      "codDocumento": "8116509",
      "tipoDocumento": "Nota Fiscal Eletrônica",
      "codTipoDocumento": 4,
      "dataDocumento": "2026-05-14T00:00:00",
      "numDocumento": "534322",
      "valorDocumento": 17.99,
      "urlDocumento": "http://www.camara.leg.br/cota-parlamentar/nota-fiscal-eletronica?ideDocumentoFiscal=8116509",
      "nomeFornecedor": "TAIOBA SELF-SERVICE LTDA EPP",
      "cnpjCpfFornecedor": "03346671001330",
      "valorLiquido": 17.99,
      "valorGlosa": 0.0,
      "numRessarcimento": "",
      "codLote": 2245435,
      "parcela": 0
    },
    {
      "ano": 2026,
      "mes": 5,
      "tipoDespesa": "FORNECIMENTO DE ALIMENTAÇÃO DO PARLAMENTAR",
      "codDocumento": "8116503",
      "tipoDocumento": "Nota Fiscal Eletrônica",
      "codTipoDocumento": 4,
      "dataDocumento": "2026-05-20T00:00:00",
      "numDocumento": "539048",
      "valorDocumento": 17.99,
      "urlDocumento": "http://www.camara.leg.br/cota-parlamentar/nota-fiscal-eletronica?ideDocumentoFiscal=8116503",
      "nomeFornecedor": "TAIOBA SELF-SERVICE LTDA EPP",
      "cnpjCpfFornecedor": "03346671001330",
      "valorLiquido": 17.99,
      "valorGlosa": 0.0,
      "numRessarcimento": "",
      "codLote": 2245435,
      "parcela": 0
    },
    {
      "ano": 2026,
      "mes": 5,
      "tipoDespesa": "FORNECIMENTO DE ALIMENTAÇÃO DO PARLAMENTAR",
      "codDocumento": "8116506",
      "tipoDocumento": "Nota Fiscal Eletrônica",
      "codTipoDocumento": 4,
      "dataDocumento": "2026-05-15T00:00:00",
      "numDocumento": "4035",
      "valorDocumento": 27.0,
      "urlDocumento": "http://www.camara.leg.br/cota-parlamentar/nota-fiscal-eletronica?ideDocumentoFiscal=8116506",
      "nomeFornecedor": "VOVO DALVA COMERCIO DE ALIMENTOS LTDA",
      "cnpjCpfFornecedor": "04337380000105",
      "valorLiquido": 27.0,
      "valorGlosa": 0.0,
      "numRessarcimento": "",
      "codLote": 2245435,
      "parcela": 0
    },
    {
      "ano": 2026,
      "mes": 5,
      "tipoDespesa": "HOSPEDAGEM ,EXCETO DO PARLAMENTAR NO DISTRITO FEDERAL.",
      "codDocumento": "8107464",
      "tipoDocumento": "Nota Fiscal",
      "codTipoDocumento": 0,
      "dataDocumento": "2026-05-23T00:00:00",
      "numDocumento": "263",
      "valorDocumento": 200.0,
      "urlDocumento": "https://www.camara.leg.br/cota-parlamentar/documentos/publ/2938/2026/8107464.pdf",
      "nomeFornecedor": "HOTEL E RESTAURANTE DETALHE",
      "cnpjCpfFornecedor": "30907779000194",
      "valorLiquido": 200.0,
      "valorGlosa": 0.0,
      "numRessarcimento": "",
      "codLote": 2240574,
      "parcela": 0
    },
    {
      "ano": 2026,
      "mes": 5,
      "tipoDespesa": "HOSPEDAGEM ,EXCETO DO PARLAMENTAR NO DISTRITO FEDERAL.",
      "codDocumento": "8107471",
      "tipoDocumento": "Nota Fiscal",
      "codTipoDocumento": 0,
      "dataDocumento": "2026-05-23T00:00:00",
      "numDocumento": "264",
      "valorDocumento": 100.0,
      "urlDocumento": "https://www.camara.leg.br/cota-parlamentar/documentos/publ/2938/2026/8107471.pdf",
      "nomeFornecedor": "HOTEL E RESTAURANTE DETALHE",
      "cnpjCpfFornecedor": "30907779000194",
      "valorLiquido": 100.0,
      "valorGlosa": 0.0,
      "numRessarcimento": "",
      "codLote": 2240574,
      "parcela": 0
    },
    {
      "ano": 2026,
      "mes": 5,
      "tipoDespesa": "HOSPEDAGEM ,EXCETO DO PARLAMENTAR NO DISTRITO FEDERAL.",
      "codDocumento": "8107450",
      "tipoDocumento": "Nota Fiscal",
      "codTipoDocumento": 0,
      "dataDocumento": "2026-05-23T00:00:00",
      "numDocumento": "266",
      "valorDocumento": 100.0,
      "urlDocumento": "https://www.camara.leg.br/cota-parlamentar/documentos/publ/2938/2026/8107450.pdf",
      "nomeFornecedor": "HOTEL E RESTAURANTE DETALHE",
      "cnpjCpfFornecedor": "30907779000194",
      "valorLiquido": 100.0,
      "valorGlosa": 0.0,
      "numRessarcimento": "",
      "codLote": 2240574,
      "parcela": 0
    },
    {
      "ano": 2026,
      "mes": 5,
      "tipoDespesa": "HOSPEDAGEM ,EXCETO DO PARLAMENTAR NO DISTRITO FEDERAL.",
      "codDocumento": "8107485",
      "tipoDocumento": "Nota Fiscal",
      "codTipoDocumento": 0,
      "dataDocumento": "2026-05-23T00:00:00",
      "numDocumento": "267",
      "valorDocumento": 120.0,
      "urlDocumento": "https://www.camara.leg.br/cota-parlamentar/documentos/publ/2938/2026/8107485.pdf",
      "nomeFornecedor": "HOTEL E RESTAURANTE DETALHE",
      "cnpjCpfFornecedor": "30907779000194",
      "valorLiquido": 120.0,
      "valorGlosa": 0.0,
      "numRessarcimento": "",
      "codLote": 2240574,
      "parcela": 0
    },
    {
      "ano": 2026,
      "mes": 5,
      "tipoDespesa": "HOSPEDAGEM ,EXCETO DO PARLAMENTAR NO DISTRITO FEDERAL.",
      "codDocumento": "8107408",
      "tipoDocumento": "Nota Fiscal",
      "codTipoDocumento": 0,
      "dataDocumento": "2026-05-24T00:00:00",
      "numDocumento": "2026000001342",
      "valorDocumento": 189.0,
      "urlDocumento": "https://www.camara.leg.br/cota-parlamentar/documentos/publ/2938/2026/8107408.pdf",
      "nomeFornecedor": "LEOPOLDO EMPREENDIMENTO TURISTICO LTDA",
      "cnpjCpfFornecedor": "01736026000165",
      "valorLiquido": 189.0,
      "valorGlosa": 0.0,
      "numRessarcimento": "",
      "codLote": 2240574,
      "parcela": 0
    },
    {
      "ano": 2026,
      "mes": 5,
      "tipoDespesa": "HOSPEDAGEM ,EXCETO DO PARLAMENTAR NO DISTRITO FEDERAL.",
      "codDocumento": "8107527",
      "tipoDocumento": "Nota Fiscal",
      "codTipoDocumento": 0,
      "dataDocumento": "2026-05-24T00:00:00",
      "numDocumento": "2026000001343",
      "valorDocumento": 189.0,
      "urlDocumento": "https://www.camara.leg.br/cota-parlamentar/documentos/publ/2938/2026/8107527.pdf",
      "nomeFornecedor": "LEOPOLDO EMPREENDIMENTO TURISTICO LTDA",
      "cnpjCpfFornecedor": "01736026000165",
      "valorLiquido": 189.0,
      "valorGlosa": 0.0,
      "numRessarcimento": "",
      "codLote": 2240574,
      "parcela": 0
    },
    {
      "ano": 2026,
      "mes": 5,
      "tipoDespesa": "HOSPEDAGEM ,EXCETO DO PARLAMENTAR NO DISTRITO FEDERAL.",
      "codDocumento": "8095474",
      "tipoDocumento": "Nota Fiscal",
      "codTipoDocumento": 0,
      "dataDocumento": "2026-05-04T00:00:00",
      "numDocumento": "378",
      "valorDocumento": 259.0,
      "urlDocumento": "https://www.camara.leg.br/cota-parlamentar/documentos/publ/2938/2026/8095474.pdf",
      "nomeFornecedor": "PAULO NOE PIRES DE CARVALHO",
      "cnpjCpfFornecedor": "30995973000179",
      "valorLiquido": 259.0,
      "valorGlosa": 0.0,
      "numRessarcimento": "",
      "codLote": 2233683,
      "parcela": 0
    },
    {
      "ano": 2026,
      "mes": 5,
      "tipoDespesa": "LOCAÇÃO OU FRETAMENTO DE VEÍCULOS AUTOMOTORES",
      "codDocumento": "8116167",
      "tipoDocumento": "Nota Fiscal",
      "codTipoDocumento": 0,
      "dataDocumento": "2026-06-03T00:00:00",
      "numDocumento": "00000144",
      "valorDocumento": 8000.0,
      "urlDocumento": "https://www.camara.leg.br/cota-parlamentar/documentos/publ/2938/2026/8116167.pdf",
      "nomeFornecedor": "CONSTRUTORA JR CONCEIÇAO LTDA",
      "cnpjCpfFornecedor": "27493891000111",
      "valorLiquido": 8000.0,
      "valorGlosa": 0.0,
      "numRessarcimento": "",
      "codLote": 2244805,
      "parcela": 0
    },
    {
      "ano": 2026,
      "mes": 5,
      "tipoDespesa": "SERVIÇO DE TÁXI, PEDÁGIO E ESTACIONAMENTO",
      "codDocumento": "8116491",
      "tipoDocumento": "Recibos/Outros",
      "codTipoDocumento": 1,
      "dataDocumento": "2026-05-06T00:00:00",
      "numDocumento": "99POP__6_5_2026_may",
      "valorDocumento": 22.35,
      "urlDocumento": "https://www.camara.leg.br/cota-parlamentar/documentos/publ/2938/2026/8116491.pdf",
      "nomeFornecedor": "99 POP",
      "cnpjCpfFornecedor": "18033552000161",
      "valorLiquido": 22.35,
      "valorGlosa": 0.0,
      "numRessarcimento": "",
      "codLote": 2244956,
      "parcela": 0
    },
    {
      "ano": 2026,
      "mes": 5,
      "tipoDespesa": "SERVIÇO DE TÁXI, PEDÁGIO E ESTACIONAMENTO",
      "codDocumento": "8116490",
      "tipoDocumento": "Recibos/Outros",
      "codTipoDocumento": 1,
      "dataDocumento": "2026-05-06T00:00:00",
      "numDocumento": "99POP__6_5_2026_may",
      "valorDocumento": 47.34,
      "urlDocumento": "https://www.camara.leg.br/cota-parlamentar/documentos/publ/2938/2026/8116490.pdf",
      "nomeFornecedor": "99 POP",
      "cnpjCpfFornecedor": "18033552000161",
      "valorLiquido": 47.34,
      "valorGlosa": 0.0,
      "numRessarcimento": "",
      "codLote": 2244956,
      "parcela": 0
    },
    {
      "ano": 2026,
      "mes": 5,
      "tipoDespesa": "SERVIÇO DE TÁXI, PEDÁGIO E ESTACIONAMENTO",
      "codDocumento": "8117439",
      "tipoDocumento": "Recibos/Outros",
      "codTipoDocumento": 1,
      "dataDocumento": "2026-05-05T00:00:00",
      "numDocumento": "S/N",
      "valorDocumento": 20.0,
      "urlDocumento": "https://www.camara.leg.br/cota-parlamentar/documentos/publ/2938/2026/8117439.pdf",
      "nomeFornecedor": "ASSOCIAÇÃO DOS TAXISTAS DO DISTRITO FEDERAL",
      "cnpjCpfFornecedor": "15695357000109",
      "valorLiquido": 20.0,
      "valorGlosa": 0.0,
      "numRessarcimento": "",
      "codLote": 2245431,
      "parcela": 0
    },
    {
      "ano": 2026,
      "mes": 5,
      "tipoDespesa": "SERVIÇO DE TÁXI, PEDÁGIO E ESTACIONAMENTO",
      "codDocumento": "8117435",
      "tipoDocumento": "Recibos/Outros",
      "codTipoDocumento": 1,
      "dataDocumento": "2026-05-05T00:00:00",
      "numDocumento": "S/N",
      "valorDocumento": 61.0,
      "urlDocumento": "https://www.camara.leg.br/cota-parlamentar/documentos/publ/2938/2026/8117435.pdf",
      "nomeFornecedor": "ASSOCIAÇÃO DOS TAXISTAS DO DISTRITO FEDERAL",
      "cnpjCpfFornecedor": "15695357000109",
      "valorLiquido": 61.0,
      "valorGlosa": 0.0,
      "numRessarcimento": "",
      "codLote": 2245431,
      "parcela": 0
    },
    {
      "ano": 2026,
      "mes": 5,
      "tipoDespesa": "SERVIÇO DE TÁXI, PEDÁGIO E ESTACIONAMENTO",
      "codDocumento": "8098750",
      "tipoDocumento": "Recibos/Outros",
      "codTipoDocumento": 1,
      "dataDocumento": "2026-05-06T00:00:00",
      "numDocumento": "TX_10498_5_2026",
      "valorDocumento": 26.0,
      "urlDocumento": "https://www.camara.leg.br/cota-parlamentar/documentos/publ/2938/2026/8098750.pdf",
      "nomeFornecedor": "ASSOCIAÇÃO DOS TAXISTAS DO DISTRITO FEDERAL",
      "cnpjCpfFornecedor": "15695357000109",
      "valorLiquido": 26.0,
      "valorGlosa": 0.0,
      "numRessarcimento": "",
      "codLote": 2235513,
      "parcela": 0
    },
    {
      "ano": 2026,
      "mes": 5,
      "tipoDespesa": "SERVIÇO DE TÁXI, PEDÁGIO E ESTACIONAMENTO",
      "codDocumento": "8117443",
      "tipoDocumento": "Recibos/Outros",
      "codTipoDocumento": 1,
      "dataDocumento": "2026-05-05T00:00:00",
      "numDocumento": "TX_1959_5_2026",
      "valorDocumento": 18.0,
      "urlDocumento": "https://www.camara.leg.br/cota-parlamentar/documentos/publ/2938/2026/8117443.pdf",
      "nomeFornecedor": "ASSOCIAÇÃO DOS TAXISTAS DO DISTRITO FEDERAL",
      "cnpjCpfFornecedor": "15695357000109",
      "valorLiquido": 18.0,
      "valorGlosa": 0.0,
      "numRessarcimento": "",
      "codLote": 2245432,
      "parcela": 0
    },
    {
      "ano": 2026,
      "mes": 5,
      "tipoDespesa": "SERVIÇO DE TÁXI, PEDÁGIO E ESTACIONAMENTO",
      "codDocumento": "8098751",
      "tipoDocumento": "Recibos/Outros",
      "codTipoDocumento": 1,
      "dataDocumento": "2026-05-06T00:00:00",
      "numDocumento": "TX_3393_5_2026",
      "valorDocumento": 24.0,
      "urlDocumento": "https://www.camara.leg.br/cota-parlamentar/documentos/publ/2938/2026/8098751.pdf",
      "nomeFornecedor": "ASSOCIAÇÃO DOS TAXISTAS DO DISTRITO FEDERAL",
      "cnpjCpfFornecedor": "15695357000109",
      "valorLiquido": 24.0,
      "valorGlosa": 0.0,
      "numRessarcimento": "",
      "codLote": 2235513,
      "parcela": 0
    },
    {
      "ano": 2026,
      "mes": 5,
      "tipoDespesa": "SERVIÇO DE TÁXI, PEDÁGIO E ESTACIONAMENTO",
      "codDocumento": "8098748",
      "tipoDocumento": "Recibos/Outros",
      "codTipoDocumento": 1,
      "dataDocumento": "2026-05-06T00:00:00",
      "numDocumento": "TX_4015_5_2026",
      "valorDocumento": 75.0,
      "urlDocumento": "https://www.camara.leg.br/cota-parlamentar/documentos/publ/2938/2026/8098748.pdf",
      "nomeFornecedor": "ASSOCIAÇÃO DOS TAXISTAS DO DISTRITO FEDERAL",
      "cnpjCpfFornecedor": "15695357000109",
      "valorLiquido": 75.0,
      "valorGlosa": 0.0,
      "numRessarcimento": "",
      "codLote": 2235513,
      "parcela": 0
    },
    {
      "ano": 2026,
      "mes": 5,
      "tipoDespesa": "SERVIÇO DE TÁXI, PEDÁGIO E ESTACIONAMENTO",
      "codDocumento": "8098753",
      "tipoDocumento": "Recibos/Outros",
      "codTipoDocumento": 1,
      "dataDocumento": "2026-05-05T00:00:00",
      "numDocumento": "TX_5287_5_2026",
      "valorDocumento": 20.0,
      "urlDocumento": "https://www.camara.leg.br/cota-parlamentar/documentos/publ/2938/2026/8098753.pdf",
      "nomeFornecedor": "ASSOCIAÇÃO DOS TAXISTAS DO DISTRITO FEDERAL",
      "cnpjCpfFornecedor": "15695357000109",
      "valorLiquido": 20.0,
      "valorGlosa": 0.0,
      "numRessarcimento": "",
      "codLote": 2235513,
      "parcela": 0
    },
    {
      "ano": 2026,
      "mes": 5,
      "tipoDespesa": "SERVIÇO DE TÁXI, PEDÁGIO E ESTACIONAMENTO",
      "codDocumento": "8098754",
      "tipoDocumento": "Recibos/Outros",
      "codTipoDocumento": 1,
      "dataDocumento": "2026-05-05T00:00:00",
      "numDocumento": "TX_7110_5_2026",
      "valorDocumento": 14.0,
      "urlDocumento": "https://www.camara.leg.br/cota-parlamentar/documentos/publ/2938/2026/8098754.pdf",
      "nomeFornecedor": "ASSOCIAÇÃO DOS TAXISTAS DO DISTRITO FEDERAL",
      "cnpjCpfFornecedor": "15695357000109",
      "valorLiquido": 14.0,
      "valorGlosa": 0.0,
      "numRessarcimento": "",
      "codLote": 2235513,
      "parcela": 0
    },
    {
      "ano": 2026,
      "mes": 5,
      "tipoDespesa": "SERVIÇO DE TÁXI, PEDÁGIO E ESTACIONAMENTO",
      "codDocumento": "8098752",
      "tipoDocumento": "Recibos/Outros",
      "codTipoDocumento": 1,
      "dataDocumento": "2026-05-05T00:00:00",
      "numDocumento": "TX_9882_5_2026",
      "valorDocumento": 61.0,
      "urlDocumento": "https://www.camara.leg.br/cota-parlamentar/documentos/publ/2938/2026/8098752.pdf",
      "nomeFornecedor": "ASSOCIAÇÃO DOS TAXISTAS DO DISTRITO FEDERAL",
      "cnpjCpfFornecedor": "15695357000109",
      "valorLiquido": 61.0,
      "valorGlosa": 0.0,
      "numRessarcimento": "",
      "codLote": 2235513,
      "parcela": 0
    },
    {
      "ano": 2026,
      "mes": 5,
      "tipoDespesa": "SERVIÇO DE TÁXI, PEDÁGIO E ESTACIONAMENTO",
      "codDocumento": "8116561",
      "tipoDocumento": "Recibos/Outros",
      "codTipoDocumento": 1,
      "dataDocumento": "2026-05-05T00:00:00",
      "numDocumento": "S/N",
      "valorDocumento": 40.0,
      "urlDocumento": "https://www.camara.leg.br/cota-parlamentar/documentos/publ/2938/2026/8116561.pdf",
      "nomeFornecedor": "COOBRAS RADIO TAXI",
      "cnpjCpfFornecedor": "00521294000105",
      "valorLiquido": 40.0,
      "valorGlosa": 0.0,
      "numRessarcimento": "",
      "codLote": 2245431,
      "parcela": 0
    },
    {
      "ano": 2026,
      "mes": 5,
      "tipoDespesa": "SERVIÇO DE TÁXI, PEDÁGIO E ESTACIONAMENTO",
      "codDocumento": "8098747",
      "tipoDocumento": "Recibos/Outros",
      "codTipoDocumento": 1,
      "dataDocumento": "2026-05-05T00:00:00",
      "numDocumento": "TX_10380_5_2026",
      "valorDocumento": 40.0,
      "urlDocumento": "https://www.camara.leg.br/cota-parlamentar/documentos/publ/2938/2026/8098747.pdf",
      "nomeFornecedor": "COOBRAS RADIO TAXI",
      "cnpjCpfFornecedor": "00521294000105",
      "valorLiquido": 40.0,
      "valorGlosa": 0.0,
      "numRessarcimento": "",
      "codLote": 2235513,
      "parcela": 0
    },
    {
      "ano": 2026,
      "mes": 5,
      "tipoDespesa": "SERVIÇO DE TÁXI, PEDÁGIO E ESTACIONAMENTO",
      "codDocumento": "8112514",
      "tipoDocumento": "Recibos/Outros",
      "codTipoDocumento": 1,
      "dataDocumento": "2026-05-05T00:00:00",
      "numDocumento": "UBER_Airton_5_2026",
      "valorDocumento": 81.99,
      "urlDocumento": "https://www.camara.leg.br/cota-parlamentar/documentos/publ/2938/2026/8112514.pdf",
      "nomeFornecedor": "UBER DO BRASIL TECNOLOGIA LTDA.",
      "cnpjCpfFornecedor": "17895646000187",
      "valorLiquido": 81.99,
      "valorGlosa": 0.0,
      "numRessarcimento": "",
      "codLote": 2242862,
      "parcela": 0
    },
    {
      "ano": 2026,
      "mes": 5,
      "tipoDespesa": "SERVIÇO DE TÁXI, PEDÁGIO E ESTACIONAMENTO",
      "codDocumento": "8112510",
      "tipoDocumento": "Recibos/Outros",
      "codTipoDocumento": 1,
      "dataDocumento": "2026-05-20T00:00:00",
      "numDocumento": "UBER_Caio_5_2026",
      "valorDocumento": 58.99,
      "urlDocumento": "https://www.camara.leg.br/cota-parlamentar/documentos/publ/2938/2026/8112510.pdf",
      "nomeFornecedor": "UBER DO BRASIL TECNOLOGIA LTDA.",
      "cnpjCpfFornecedor": "17895646000187",
      "valorLiquido": 58.99,
      "valorGlosa": 0.0,
      "numRessarcimento": "",
      "codLote": 2242862,
      "parcela": 0
    },
    {
      "ano": 2026,
      "mes": 5,
      "tipoDespesa": "SERVIÇO DE TÁXI, PEDÁGIO E ESTACIONAMENTO",
      "codDocumento": "8116489",
      "tipoDocumento": "Recibos/Outros",
      "codTipoDocumento": 1,
      "dataDocumento": "2026-05-28T00:00:00",
      "numDocumento": "Uber_Carlos_5_2026_ma",
      "valorDocumento": 40.95,
      "urlDocumento": "https://www.camara.leg.br/cota-parlamentar/documentos/publ/2938/2026/8116489.pdf",
      "nomeFornecedor": "UBER DO BRASIL TECNOLOGIA LTDA.",
      "cnpjCpfFornecedor": "17895646000187",
      "valorLiquido": 40.95,
      "valorGlosa": 0.0,
      "numRessarcimento": "",
      "codLote": 2244956,
      "parcela": 0
    },
    {
      "ano": 2026,
      "mes": 5,
      "tipoDespesa": "SERVIÇO DE TÁXI, PEDÁGIO E ESTACIONAMENTO",
      "codDocumento": "8107442",
      "tipoDocumento": "Recibos/Outros",
      "codTipoDocumento": 1,
      "dataDocumento": "2026-05-28T00:00:00",
      "numDocumento": "Uber_Carlos_5_2026_may",
      "valorDocumento": 40.95,
      "urlDocumento": "https://www.camara.leg.br/cota-parlamentar/documentos/publ/2938/2026/8107442.pdf",
      "nomeFornecedor": "UBER DO BRASIL TECNOLOGIA LTDA.",
      "cnpjCpfFornecedor": "17895646000187",
      "valorLiquido": 40.95,
      "valorGlosa": 0.0,
      "numRessarcimento": "",
      "codLote": 2240574,
      "parcela": 0
    },
    {
      "ano": 2026,
      "mes": 5,
      "tipoDespesa": "SERVIÇO DE TÁXI, PEDÁGIO E ESTACIONAMENTO",
      "codDocumento": "8112516",
      "tipoDocumento": "Recibos/Outros",
      "codTipoDocumento": 1,
      "dataDocumento": "2026-04-29T00:00:00",
      "numDocumento": "UBER_Geraldo_4_2026",
      "valorDocumento": 75.95,
      "urlDocumento": "https://www.camara.leg.br/cota-parlamentar/documentos/publ/2938/2026/8112516.pdf",
      "nomeFornecedor": "UBER DO BRASIL TECNOLOGIA LTDA.",
      "cnpjCpfFornecedor": "17895646000187",
      "valorLiquido": 75.95,
      "valorGlosa": 0.0,
      "numRessarcimento": "",
      "codLote": 2242862,
      "parcela": 0
    },
    {
      "ano": 2026,
      "mes": 5,
      "tipoDespesa": "SERVIÇO DE TÁXI, PEDÁGIO E ESTACIONAMENTO",
      "codDocumento": "8112519",
      "tipoDocumento": "Recibos/Outros",
      "codTipoDocumento": 1,
      "dataDocumento": "2026-05-13T00:00:00",
      "numDocumento": "UBER_Iran_5_2026",
      "valorDocumento": 15.97,
      "urlDocumento": "https://www.camara.leg.br/cota-parlamentar/documentos/publ/2938/2026/8112519.pdf",
      "nomeFornecedor": "UBER DO BRASIL TECNOLOGIA LTDA.",
      "cnpjCpfFornecedor": "17895646000187",
      "valorLiquido": 15.97,
      "valorGlosa": 0.0,
      "numRessarcimento": "",
      "codLote": 2242862,
      "parcela": 0
    },
    {
      "ano": 2026,
      "mes": 5,
      "tipoDespesa": "SERVIÇO DE TÁXI, PEDÁGIO E ESTACIONAMENTO",
      "codDocumento": "8112512",
      "tipoDocumento": "Recibos/Outros",
      "codTipoDocumento": 1,
      "dataDocumento": "2026-05-12T00:00:00",
      "numDocumento": "UBER_Jonas_5_2026",
      "valorDocumento": 69.98,
      "urlDocumento": "https://www.camara.leg.br/cota-parlamentar/documentos/publ/2938/2026/8112512.pdf",
      "nomeFornecedor": "UBER DO BRASIL TECNOLOGIA LTDA.",
      "cnpjCpfFornecedor": "17895646000187",
      "valorLiquido": 69.98,
      "valorGlosa": 0.0,
      "numRessarcimento": "",
      "codLote": 2242862,
      "parcela": 0
    },
    {
      "ano": 2026,
      "mes": 5,
      "tipoDespesa": "SERVIÇO DE TÁXI, PEDÁGIO E ESTACIONAMENTO",
      "codDocumento": "8112505",
      "tipoDocumento": "Recibos/Outros",
      "codTipoDocumento": 1,
      "dataDocumento": "2026-05-14T00:00:00",
      "numDocumento": "UBER_Luisvaldo_5_2026",
      "valorDocumento": 42.99,
      "urlDocumento": "https://www.camara.leg.br/cota-parlamentar/documentos/publ/2938/2026/8112505.pdf",
      "nomeFornecedor": "UBER DO BRASIL TECNOLOGIA LTDA.",
      "cnpjCpfFornecedor": "17895646000187",
      "valorLiquido": 42.99,
      "valorGlosa": 0.0,
      "numRessarcimento": "",
      "codLote": 2242862,
      "parcela": 0
    },
    {
      "ano": 2026,
      "mes": 5,
      "tipoDespesa": "SERVIÇO DE TÁXI, PEDÁGIO E ESTACIONAMENTO",
      "codDocumento": "8112517",
      "tipoDocumento": "Recibos/Outros",
      "codTipoDocumento": 1,
      "dataDocumento": "2026-05-13T00:00:00",
      "numDocumento": "UBER_LUIZVALDO_5_2026",
      "valorDocumento": 13.99,
      "urlDocumento": "https://www.camara.leg.br/cota-parlamentar/documentos/publ/2938/2026/8112517.pdf",
      "nomeFornecedor": "UBER DO BRASIL TECNOLOGIA LTDA.",
      "cnpjCpfFornecedor": "17895646000187",
      "valorLiquido": 13.99,
      "valorGlosa": 0.0,
      "numRessarcimento": "",
      "codLote": 2242862,
      "parcela": 0
    },
    {
      "ano": 2026,
      "mes": 5,
      "tipoDespesa": "SERVIÇO DE TÁXI, PEDÁGIO E ESTACIONAMENTO",
      "codDocumento": "8112506",
      "tipoDocumento": "Recibos/Outros",
      "codTipoDocumento": 1,
      "dataDocumento": "2026-05-05T00:00:00",
      "numDocumento": "UBER_Paulo C_5_2026",
      "valorDocumento": 14.98,
      "urlDocumento": "https://www.camara.leg.br/cota-parlamentar/documentos/publ/2938/2026/8112506.pdf",
      "nomeFornecedor": "UBER DO BRASIL TECNOLOGIA LTDA.",
      "cnpjCpfFornecedor": "17895646000187",
      "valorLiquido": 14.98,
      "valorGlosa": 0.0,
      "numRessarcimento": "",
      "codLote": 2242862,
      "parcela": 0
    },
    {
      "ano": 2026,
      "mes": 5,
      "tipoDespesa": "SERVIÇO DE TÁXI, PEDÁGIO E ESTACIONAMENTO",
      "codDocumento": "8112515",
      "tipoDocumento": "Recibos/Outros",
      "codTipoDocumento": 1,
      "dataDocumento": "2026-05-12T00:00:00",
      "numDocumento": "UBER_Thiago_5_2026",
      "valorDocumento": 14.97,
      "urlDocumento": "https://www.camara.leg.br/cota-parlamentar/documentos/publ/2938/2026/8112515.pdf",
      "nomeFornecedor": "UBER DO BRASIL TECNOLOGIA LTDA.",
      "cnpjCpfFornecedor": "17895646000187",
      "valorLiquido": 14.97,
      "valorGlosa": 0.0,
      "numRessarcimento": "",
      "codLote": 2242841,
      "parcela": 0
    },
    {
      "ano": 2026,
      "mes": 5,
      "tipoDespesa": "SERVIÇO DE TÁXI, PEDÁGIO E ESTACIONAMENTO",
      "codDocumento": "8112508",
      "tipoDocumento": "Recibos/Outros",
      "codTipoDocumento": 1,
      "dataDocumento": "2026-05-08T00:00:00",
      "numDocumento": "UBER_VINICIOS_5_2026",
      "valorDocumento": 36.97,
      "urlDocumento": "https://www.camara.leg.br/cota-parlamentar/documentos/publ/2938/2026/8112508.pdf",
      "nomeFornecedor": "UBER DO BRASIL TECNOLOGIA LTDA.",
      "cnpjCpfFornecedor": "17895646000187",
      "valorLiquido": 36.97,
      "valorGlosa": 0.0,
      "numRessarcimento": "",
      "codLote": 2242862,
      "parcela": 0
    },
    {
      "ano": 2026,
      "mes": 5,
      "tipoDespesa": "PASSAGEM AÉREA - SIGEPA",
      "codDocumento": "72BAF8E1-2BF6-4F9D-8DEA-2C48205B1DEA",
      "tipoDocumento": "Nota Fiscal",
      "codTipoDocumento": 0,
      "dataDocumento": "2026-05-17T00:00:00",
      "numDocumento": "BHRMQS",
      "valorDocumento": 973.45,
      "urlDocumento": null,
      "nomeFornecedor": "Azul Linhas Aéreas",
      "cnpjCpfFornecedor": "",
      "valorLiquido": 973.45,
      "valorGlosa": 0.0,
      "numRessarcimento": "0",
      "codLote": 0,
      "parcela": 0
    },
    {
      "ano": 2026,
      "mes": 5,
      "tipoDespesa": "PASSAGEM AÉREA - SIGEPA",
      "codDocumento": "C849C745-CCAD-437F-8CF0-7BC41A819CA8",
      "tipoDocumento": "Nota Fiscal",
      "codTipoDocumento": 0,
      "dataDocumento": "2026-05-06T00:00:00",
      "numDocumento": "1272303214439",
      "valorDocumento": 1035.87,
      "urlDocumento": null,
      "nomeFornecedor": "Gol Linhas Aéreas",
      "cnpjCpfFornecedor": "",
      "valorLiquido": 1035.87,
      "valorGlosa": 0.0,
      "numRessarcimento": "0",
      "codLote": 0,
      "parcela": 0
    },
    {
      "ano": 2026,
      "mes": 5,
      "tipoDespesa": "PASSAGEM AÉREA - SIGEPA",
      "codDocumento": "B704DD63-6442-4557-B95D-E4F3BC264410",
      "tipoDocumento": "Nota Fiscal",
      "codTipoDocumento": 0,
      "dataDocumento": "2026-05-19T00:00:00",
      "numDocumento": "1272304163917",
      "valorDocumento": 1436.87,
      "urlDocumento": null,
      "nomeFornecedor": "Gol Linhas Aéreas",
      "cnpjCpfFornecedor": "",
      "valorLiquido": 1436.87,
      "valorGlosa": 0.0,
      "numRessarcimento": "0",
      "codLote": 0,
      "parcela": 0
    },
    {
      "ano": 2026,
      "mes": 5,
      "tipoDespesa": "PASSAGEM AÉREA - SIGEPA",
      "codDocumento": "A02B99B1-2176-42DC-A9AC-F326B2701894",
      "tipoDocumento": "Nota Fiscal",
      "codTipoDocumento": 0,
      "dataDocumento": "2026-05-26T00:00:00",
      "numDocumento": "1272304624608",
      "valorDocumento": 2402.81,
      "urlDocumento": null,
      "nomeFornecedor": "Gol Linhas Aéreas",
      "cnpjCpfFornecedor": "",
      "valorLiquido": 2402.81,
      "valorGlosa": 0.0,
      "numRessarcimento": "0",
      "codLote": 0,
      "parcela": 0
    },
    {
      "ano": 2026,
      "mes": 5,
      "tipoDespesa": "PASSAGEM AÉREA - SIGEPA",
      "codDocumento": "DD5A6F8D-71AC-4B33-AB38-9D8E32388554",
      "tipoDocumento": "Nota Fiscal",
      "codTipoDocumento": 0,
      "dataDocumento": "2026-05-26T00:00:00",
      "numDocumento": "1272304651111",
      "valorDocumento": 2402.81,
      "urlDocumento": null,
      "nomeFornecedor": "Gol Linhas Aéreas",
      "cnpjCpfFornecedor": "",
      "valorLiquido": 2402.81,
      "valorGlosa": 0.0,
      "numRessarcimento": "0",
      "codLote": 0,
      "parcela": 0
    },
    {
      "ano": 2026,
      "mes": 5,
      "tipoDespesa": "PASSAGEM AÉREA - SIGEPA",
      "codDocumento": "DD5A6F8D-71AC-4B33-AB38-9D8E32388554",
      "tipoDocumento": "Nota Fiscal",
      "codTipoDocumento": 0,
      "dataDocumento": "2026-05-28T00:00:00",
      "numDocumento": "1272304651111",
      "valorDocumento": -2402.81,
      "urlDocumento": null,
      "nomeFornecedor": "Gol Linhas Aéreas",
      "cnpjCpfFornecedor": "",
      "valorLiquido": -2402.81,
      "valorGlosa": 0.0,
      "numRessarcimento": "0",
      "codLote": 0,
      "parcela": 0
    }
  ],
  "links": [
    {
      "rel": "self",
      "href": "https://dadosabertos.camara.leg.br/api/v2/deputados/178857/despesas?ano=2026&mes=5&ordem=ASC&ordenarPor=ano&itens=100&pagina=1"
    },
    {
      "rel": "first",
      "href": "https://dadosabertos.camara.leg.br/api/v2/deputados/178857/despesas?ano=2026&mes=5&ordem=ASC&ordenarPor=ano&pagina=1&itens=100"
    },
    {
      "rel": "last",
      "href": "https://dadosabertos.camara.leg.br/api/v2/deputados/178857/despesas?ano=2026&mes=5&ordem=ASC&ordenarPor=ano&pagina=1&itens=100"
    }
  ]
}